CHANGELOG.md
LICENSE
trongrid_extractoor/__init__.py
trongrid_extractoor/api.py
trongrid_extractoor/config.py
trongrid_extractoor/exceptions.py
trongrid_extractoor/helpers/address_helpers.py
trongrid_extractoor/helpers/argument_parser.py
trongrid_extractoor/helpers/color_picker.py
trongrid_extractoor/helpers/csv_helper.py
trongrid_extractoor/helpers/dict_helper.py
trongrid_extractoor/helpers/rich_helpers.py
trongrid_extractoor/helpers/string_constants.py
trongrid_extractoor/helpers/string_helpers.py
trongrid_extractoor/helpers/time_helpers.py
trongrid_extractoor/helpers/url_helpers.py
trongrid_extractoor/models/function.py
trongrid_extractoor/models/function_arg.py
trongrid_extractoor/models/trc10_token.py
trongrid_extractoor/models/trc20_txn.py
trongrid_extractoor/models/tron_account.py
trongrid_extractoor/models/tron_contract.py
trongrid_extractoor/models/tron_event.py
trongrid_extractoor/models/txns/create_smart_contract_txn.py
trongrid_extractoor/models/txns/trigger_smart_contract_txn.py
trongrid_extractoor/models/txns/tron_txn.py
trongrid_extractoor/models/txns/trx_transfer.py
trongrid_extractoor/output/file_output_writer.py
trongrid_extractoor/output/output_writer.py
trongrid_extractoor/output/string_io_writer.py
trongrid_extractoor/progress_tracker.py
trongrid_extractoor/request_params.py
trongrid_extractoor/response.py
trongrid_extractoor/some_curl_request.txt
trongrid_extractoor-4.10.2.dist-info/LICENSE
trongrid_extractoor-4.10.2.dist-info/METADATA
trongrid_extractoor-4.10.2.dist-info/WHEEL
trongrid_extractoor-4.10.2.dist-info/entry_points.txt
trongrid_extractoor-4.10.2.dist-info/RECORD
