Metadata-Version: 2.1
Name: trongrid-extractoor
Version: 4.10.2
Summary: Extract transactions from the Trongrid API.
Home-page: https://chainargos.com
Author: Chain Argos
Requires-Python: >=3.10,<4.0
Classifier: Programming Language :: Python :: 3
Classifier: Programming Language :: Python :: 3.10
Classifier: Programming Language :: Python :: 3.11
Requires-Dist: base58 (>=2.1.1,<3.0.0)
Requires-Dist: pendulum (>=2.1.2,<3.0.0)
Requires-Dist: pycryptodome (>=3.18.0,<4.0.0)
Requires-Dist: requests (>=2.31.0,<3.0.0)
Requires-Dist: requests_toolbelt (>=1.0.0,<2.0.0)
Requires-Dist: rich (>=13.4.1,<14.0.0)
Requires-Dist: tenacity (>=8.2.2,<9.0.0)
